genestboost/__init__.py
genestboost/boosted_linear_model.py
genestboost/boosted_model.py
genestboost/model_data_sets.py
genestboost/type_hints.py
genestboost/link_functions/__init__.py
genestboost/link_functions/base_class.py
genestboost/link_functions/cloglog.py
genestboost/link_functions/identity.py
genestboost/link_functions/log_links.py
genestboost/link_functions/logit.py
genestboost/link_functions/power_links.py
genestboost/loss_functions/__init__.py
genestboost/loss_functions/absolute_value.py
genestboost/loss_functions/base_class.py
genestboost/loss_functions/beta_loss.py
genestboost/loss_functions/least_squares.py
genestboost/loss_functions/log_cosh.py
genestboost/loss_functions/log_loss.py
genestboost/loss_functions/poisson.py
genestboost/loss_functions/quantile.py
genestboost/loss_functions/quasilog_loss.py
genestboost/loss_functions/students_t.py
genestboost/utils/__init__.py
genestboost/utils/gradients.py
genestboost/weak_learners/__init__.py
genestboost/weak_learners/simple_pls.py
tests/.coveragerc
tests/__init__.py
tests/boosted_model_test.py
tests/conftest.py
tests/initial_model_class_test.py
tests/link_functions/__init__.py
tests/link_functions/link_function_test.py
tests/link_functions/link_test_list.py
tests/loss_functions/__init__.py
tests/loss_functions/beta_loss_test.py
tests/loss_functions/loss_function_test.py
tests/loss_functions/loss_test_list.py
tests/utils/__init__.py
tests/utils/gradients_test.py
tests/weak_learners/__init__.py
tests/weak_learners/simple_pls_data.py
tests/weak_learners/simple_pls_test.py
genestboost-0.3.1.dist-info/AUTHORS
genestboost-0.3.1.dist-info/LICENSE.txt
genestboost-0.3.1.dist-info/METADATA
genestboost-0.3.1.dist-info/WHEEL
genestboost-0.3.1.dist-info/top_level.txt
genestboost-0.3.1.dist-info/RECORD
